rstcloth/__init__.py
rstcloth/cloth.py
rstcloth/rstcloth_builder.py
rstcloth2-0.3.0.dist-info/METADATA
rstcloth2-0.3.0.dist-info/RECORD
rstcloth2-0.3.0.dist-info/WHEEL
rstcloth2-0.3.0.dist-info/entry_points.txt
rstcloth2-0.3.0.dist-info/top_level.txt
