Metadata-Version: 2.1
Name: rstcloth2
Version: 0.3.0
Summary: A simple Python API for generating RestructuredText.
Home-page: http://cyborginstitute.org/projects/rstcloth
Author: Sam Kleinman
Author-email: sam@tychoish.com
License: Apache
Platform: UNKNOWN
Classifier: Programming Language :: Python
Classifier: Programming Language :: Python :: 2.7
Classifier: Programming Language :: Python :: 3
Classifier: License :: OSI Approved :: Apache Software License
Classifier: Topic :: Software Development :: Build Tools
Classifier: Topic :: Documentation
Classifier: Topic :: Text Processing
